songsdownload/__init__.py
songsdownload-1.0.10.dist-info/LICENSE
songsdownload-1.0.10.dist-info/METADATA
songsdownload-1.0.10.dist-info/WHEEL
songsdownload-1.0.10.dist-info/top_level.txt
songsdownload-1.0.10.dist-info/RECORD
