Metadata-Version: 2.1
Name: songsdownload
Version: 1.0.10
Summary: Download Sinhala Songs and Lyrics Easily
Home-page: UNKNOWN
Author: Ashen Ranaweera
Author-email: ashen8810@gmail.com
License: MIT
Keywords: python,songs,sinhala,lyrics,download,internet
Platform: UNKNOWN
Classifier: License :: OSI Approved :: MIT License
Classifier: Programming Language :: Python :: 3.6
Classifier: Programming Language :: Python :: 3.7
Classifier: Programming Language :: Python :: 3.8
Requires-Dist: google
Requires-Dist: bs4
Requires-Dist: tqdm
